MANIFEST.in
README.md
meta.json
setup.py
en_aesops_sentiment/__init__.py
en_aesops_sentiment/meta.json
en_aesops_sentiment.egg-info/PKG-INFO
en_aesops_sentiment.egg-info/SOURCES.txt
en_aesops_sentiment.egg-info/dependency_links.txt
en_aesops_sentiment.egg-info/entry_points.txt
en_aesops_sentiment.egg-info/not-zip-safe
en_aesops_sentiment.egg-info/requires.txt
en_aesops_sentiment.egg-info/top_level.txt
en_aesops_sentiment/en_aesops_sentiment-0.0.0/README.md
en_aesops_sentiment/en_aesops_sentiment-0.0.0/config.cfg
en_aesops_sentiment/en_aesops_sentiment-0.0.0/meta.json
en_aesops_sentiment/en_aesops_sentiment-0.0.0/tokenizer
en_aesops_sentiment/en_aesops_sentiment-0.0.0/textcat/cfg
en_aesops_sentiment/en_aesops_sentiment-0.0.0/textcat/model
en_aesops_sentiment/en_aesops_sentiment-0.0.0/vocab/key2row
en_aesops_sentiment/en_aesops_sentiment-0.0.0/vocab/lookups.bin
en_aesops_sentiment/en_aesops_sentiment-0.0.0/vocab/strings.json
en_aesops_sentiment/en_aesops_sentiment-0.0.0/vocab/vectors
en_aesops_sentiment/en_aesops_sentiment-0.0.0/vocab/vectors.cfg