Metadata-Version: 2.1
Name: en-aesops-sentiment
Version: 0.0.0
Home-page: 
Author: 
Author-email: 
